spontit/__init__.py
spontit/examples.py
spontit/resource.py
spontit/util.py
spontit/examples/__init__.py
spontit/examples/dirty_image_upload_example.py
spontit/examples/examples.py
spontit_pkg/__init__.py
spontit_pkg/resource.py
spontit_pkg/util.py
spontit-1.0.8.dist-info/LICENSE
spontit-1.0.8.dist-info/METADATA
spontit-1.0.8.dist-info/WHEEL
spontit-1.0.8.dist-info/top_level.txt
spontit-1.0.8.dist-info/RECORD
