Metadata-Version: 2.1
Name: spontit
Version: 1.0.8
Summary: Send push notifications without your app, website, or notification infrastructure.
Home-page: https://github.com/spontit/spontit-api-python-wrapper
Author: Spontit Inc
Author-email: info@spontit.com
License: UNKNOWN
Platform: UNKNOWN
Classifier: Programming Language :: Python :: 3
Classifier: License :: OSI Approved :: MIT License
Classifier: Operating System :: OS Independent
Requires-Python: >=3.6
